weaviate_agent_demo/__init__.py
weaviate_agent_demo/cli.py
weaviate_agent_demo/coder.py
weaviate_agent_demo/db.py
weaviate_agent_demo/db_setup/1_create_collection.py
weaviate_agent_demo/db_setup/2_import.py
weaviate_agent_demo/db_setup/3_test_query.py
weaviate_agent_demo/db_setup/9_create_cache_collection.py
weaviate_agent_demo/db_setup/__init__.py
weaviate_agent_demo/llm.py
weaviate_agent_demo/prompts.py
weaviate_agent_demo/setup.py
weaviate_agent_demo/tools.py
weaviate_agent_demo/utils.py
weaviate_agent_demo-0.3.1.dist-info/METADATA
weaviate_agent_demo-0.3.1.dist-info/WHEEL
weaviate_agent_demo-0.3.1.dist-info/entry_points.txt
weaviate_agent_demo-0.3.1.dist-info/RECORD
