Metadata-Version: 2.1
Name: weaviate-agent-demo
Version: 0.3.1
Summary: Demo project for sometimes (poorly) generating Python code for Weaviate
License: MIT
Author: JP Hwang
Author-email: me@jphwang.com
Requires-Python: >=3.9, !=2.7.*, !=3.0.*, !=3.1.*, !=3.2.*, !=3.3.*, !=3.4.*, !=3.5.*, !=3.6.*, !=3.7.*, !=3.8.*
Classifier: License :: OSI Approved :: MIT License
Classifier: Programming Language :: Python :: 3
Classifier: Programming Language :: Python :: 3.9
Classifier: Programming Language :: Python :: 3.10
Classifier: Programming Language :: Python :: 3.11
Classifier: Programming Language :: Python :: 3.12
Requires-Dist: claudette (>=0.0.9,<0.0.10)
Requires-Dist: click (>=8.1.7,<9.0.0)
Requires-Dist: streamlit (>=1.38.0,<2.0.0)
Requires-Dist: weaviate-client (>=4.7.1,<5.0.0)
